dearpygui/managers/__init__.py
dearpygui/managers/fonts/__init__.py
dearpygui/managers/fonts/font.py
dearpygui/managers/fonts/fonts.py
dearpygui/managers/py.typed
dearpygui/managers/types.py
dearpygui_managers-0.1.0.dist-info/LICENSE
dearpygui_managers-0.1.0.dist-info/METADATA
dearpygui_managers-0.1.0.dist-info/WHEEL
dearpygui_managers-0.1.0.dist-info/RECORD
